pyjazzcash/__init__.py
pyjazzcash/base_client.py
pyjazzcash/card.py
pyjazzcash/cli.py
pyjazzcash-0.1.0.dist-info/AUTHORS.rst
pyjazzcash-0.1.0.dist-info/LICENSE
pyjazzcash-0.1.0.dist-info/METADATA
pyjazzcash-0.1.0.dist-info/WHEEL
pyjazzcash-0.1.0.dist-info/entry_points.txt
pyjazzcash-0.1.0.dist-info/top_level.txt
pyjazzcash-0.1.0.dist-info/RECORD
